setup.py
examples/example1.py
examples/example2.py
examples/example3.py
examples/old_time_tests/time_test.py
examples/old_time_tests/time_test_recursivity.py
examples/old_time_tests/time_test_recursivity_single_iteration.py
examples/old_time_tests/time_test_single_iteration.py
examples/time_tests/squirrel3.py
examples/time_tests/time_test_all_dice_end.py
examples/time_tests/time_test_all_dice_iterative.py
examples/time_tests/time_test_all_dice_precomp.py
examples/time_tests/time_test_dice_end.py
examples/time_tests/time_test_dice_iterative.py
examples/time_tests/time_test_dice_precomp.py
examples/time_tests/time_test_independent_end.py
examples/time_tests/time_test_independent_iterative.py
examples/time_tests/time_test_independent_precomp.py
examples/time_tests/time_test_recursive_end.py
examples/time_tests/time_test_recursive_iterative.py
examples/time_tests/time_test_recursive_iterative_improved.py
examples/time_tests/time_test_recursive_precomp.py
preCompilation/PreCompilation.py
preCompilation/__init__.py
subjective_examples/example1.py
problogprecompilation-0.0.1.dist-info/METADATA
problogprecompilation-0.0.1.dist-info/WHEEL
problogprecompilation-0.0.1.dist-info/licenses/LICENSE
problogprecompilation-0.0.1.dist-info/RECORD
