Metadata-Version: 2.1
Name: ProbLogPreCompilation
Version: 0.0.1
Summary: A tool that allows for the easy re-use of pre-compiled ACs in ProbLog, allowing for a faster evaluation of repeated queries.
Project-URL: Homepage, https://github.com/MarcRoigVilamala/PreCompilation
Project-URL: Bug Tracker, https://github.com/MarcRoigVilamala/PreCompilation/issues
Author-email: Marc Roig Vilamala <marc.roig.vilamala@gmail.com>
License: MIT License
License-File: LICENSE
Classifier: License :: OSI Approved :: MIT License
Classifier: Operating System :: OS Independent
Classifier: Programming Language :: Python :: 3
Requires-Python: >=3.7
Requires-Dist: problog
